{
    "1988-01-06": {
        "launches": [
            {
                "date": "1988-01-06",
                "id": "1988-001",
                "time": 7.68,
                "site": "",
                "rocket": "Tsiklon-3",
                "lat": 62.9,
                "lon": 40.5,
                "smc": false,
                "location": "53-y Nauchno-Issledovatelskiy Ispitatelniy Poligon,",
                "emissions": {
                    "BC": 0.6868747189134614,
                    "CO": 1.4627346627604858,
                    "CO2": 41.10299779988749,
                    "NOx": 2.1011553614862866,
                    "H2O": 56.52834032917984,
                    "Cly": 0.0,
                    "Al2O3": 0.0
                }
            }
        ],
        "reentries": []
    },
    "1988-01-15": {
        "launches": [
            {
                "date": "1988-01-15",
                "id": "1988-002",
                "time": 3.82,
                "site": "",
                "rocket": "Tsiklon-3",
                "lat": 62.9,
                "lon": 40.5,
                "smc": false,
                "location": "53-y Nauchno-Issledovatelskiy Ispitatelniy Poligon,",
                "emissions": {
                    "BC": 0.6868747189134614,
                    "CO": 1.4627346627604858,
                    "CO2": 41.10299779988749,
                    "NOx": 2.1011553614862866,
                    "H2O": 56.52834032917984,
                    "Cly": 0.0,
                    "Al2O3": 0.0
                }
            }
        ],
        "reentries": []
    },
    "1988-01-18": {
        "launches": [],
        "reentries": []
    },
    "1988-01-20": {
        "launches": [
            {
                "date": "1988-01-20",
                "id": "1988-003",
                "time": 22.85,
                "site": "",
                "rocket": "Soyuz-U2",
                "lat": 46.0,
                "lon": 63.0,
                "smc": false,
                "location": "NIIP-5, Baykonur, Kazakstan",
                "emissions": {
                    "BC": 1.0935036055473257,
                    "CO": 8.366101332339973,
                    "CO2": 120.33284918913668,
                    "NOx": 0.5917722364437797,
                    "H2O": 50.42076916997716,
                    "Cly": 0.0,
                    "Al2O3": 0.0
                }
            }
        ],
        "reentries": []
    },
    "1988-01-26": {
        "launches": [
            {
                "date": "1988-01-26",
                "id": "1988-004",
                "time": 11.33,
                "site": "",
                "rocket": "Soyuz-U",
                "lat": 62.9,
                "lon": 40.5,
                "smc": false,
                "location": "53-y Nauchno-Issledovatelskiy Ispitatelniy Poligon,",
                "emissions": {
                    "BC": 1.0935036055473257,
                    "CO": 8.366101332339973,
                    "CO2": 120.33284918913668,
                    "NOx": 0.5917722364437797,
                    "H2O": 50.42076916997716,
                    "Cly": 0.0,
                    "Al2O3": 0.0
                }
            }
        ],
        "reentries": []
    },
    "1988-01-30": {
        "launches": [
            {
                "date": "1988-01-30",
                "id": "1988-005",
                "time": 10.98,
                "site": "",
                "rocket": "Tsiklon-3",
                "lat": 62.9,
                "lon": 40.5,
                "smc": false,
                "location": "53-y Nauchno-Issledovatelskiy Ispitatelniy Poligon,",
                "emissions": {
                    "BC": 0.6868747189134614,
                    "CO": 1.4627346627604858,
                    "CO2": 41.10299779988749,
                    "NOx": 2.1011553614862866,
                    "H2O": 56.52834032917984,
                    "Cly": 0.0,
                    "Al2O3": 0.0
                }
            }
        ],
        "reentries": []
    },
    "1988-02-03": {
        "launches": [
            {
                "date": "1988-02-03",
                "id": "1988-006",
                "time": 5.88,
                "site": "",
                "rocket": "Atlas E",
                "lat": 34.63,
                "lon": -120.61,
                "smc": false,
                "location": "South Vandenberg AFB, California",
                "emissions": {
                    "BC": 0.715773602717771,
                    "CO": 4.772669445530476,
                    "CO2": 82.63622617465901,
                    "NOx": 0.4086085816305048,
                    "H2O": 34.04822142857137,
                    "Cly": 0.0,
                    "Al2O3": 0.0
                }
            },
            {
                "date": "1988-02-03",
                "id": "1988-007",
                "time": 12.23,
                "site": "",
                "rocket": "Soyuz-U",
                "lat": 46.0,
                "lon": 63.0,
                "smc": false,
                "location": "NIIP-5, Baykonur, Kazakstan",
                "emissions": {
                    "BC": 1.0935036055473257,
                    "CO": 8.366101332339973,
                    "CO2": 120.33284918913668,
                    "NOx": 0.5917722364437797,
                    "H2O": 50.42076916997716,
                    "Cly": 0.0,
                    "Al2O3": 0.0
                }
            }
        ],
        "reentries": []
    },
    "1988-02-08": {
        "launches": [
            {
                "date": "1988-02-08",
                "id": "1988-008",
                "time": 22.12,
                "site": "",
                "rocket": "Delta 3910",
                "lat": 28.46,
                "lon": -80.54,
                "smc": false,
                "location": "Cape Canaveral Air Station, Florida",
                "emissions": {
                    "BC": 0.5593023441201456,
                    "CO": 3.5008395157051937,
                    "CO2": 62.98617013650736,
                    "NOx": 0.34463761114366437,
                    "H2O": 29.110512700952327,
                    "Cly": 2.0180990753301513,
                    "Al2O3": 3.0504
                }
            }
        ],
        "reentries": []
    },
    "1988-02-17": {
        "launches": [
            {
                "date": "1988-02-17",
                "id": "1988-009",
                "time": 0.38,
                "site": "",
                "rocket": "Proton-K/DM-2",
                "lat": 46.0,
                "lon": 63.0,
                "smc": false,
                "location": "NIIP-5, Baykonur, Kazakstan",
                "emissions": {
                    "BC": 2.1624429718465246,
                    "CO": 4.549336216904315,
                    "CO2": 146.13061133955784,
                    "NOx": 7.56439493696129,
                    "H2O": 199.63896572145242,
                    "Cly": 0.0,
                    "Al2O3": 0.0
                }
            }
        ],
        "reentries": []
    },
    "1988-02-18": {
        "launches": [
            {
                "date": "1988-02-18",
                "id": "1988-010",
                "time": 9.82,
                "site": "",
                "rocket": "Soyuz-U",
                "lat": 62.9,
                "lon": 40.5,
                "smc": false,
                "location": "53-y Nauchno-Issledovatelskiy Ispitatelniy Poligon,",
                "emissions": {
                    "BC": 1.0935036055473257,
                    "CO": 8.366101332339973,
                    "CO2": 120.33284918913668,
                    "NOx": 0.5917722364437797,
                    "H2O": 50.42076916997716,
                    "Cly": 0.0,
                    "Al2O3": 0.0
                }
            }
        ],
        "reentries": []
    },
    "1988-02-19": {
        "launches": [
            {
                "date": "1988-02-19",
                "id": "1988-011",
                "time": 8.0,
                "site": "",
                "rocket": "Soyuz-U",
                "lat": 46.0,
                "lon": 63.0,
                "smc": false,
                "location": "NIIP-5, Baykonur, Kazakstan",
                "emissions": {
                    "BC": 1.0935036055473257,
                    "CO": 8.366101332339973,
                    "CO2": 120.33284918913668,
                    "NOx": 0.5917722364437797,
                    "H2O": 50.42076916997716,
                    "Cly": 0.0,
                    "Al2O3": 0.0
                }
            },
            {
                "date": "1988-02-19",
                "id": "1988-012",
                "time": 10.08,
                "site": "",
                "rocket": "H-1",
                "lat": 30.4,
                "lon": 130.97,
                "smc": false,
                "location": "Tanegashima Space Center, Tanegashima, Nippon",
                "emissions": {
                    "BC": 0.5309432643851177,
                    "CO": 3.4727315188310923,
                    "CO2": 61.37123038799858,
                    "NOx": 0.31854308264185827,
                    "H2O": 26.44057239047615,
                    "Cly": 0.7453947168866696,
                    "Al2O3": 1.1266800000000001
                }
            }
        ],
        "reentries": []
    },
    "1988-02-26": {
        "launches": [
            {
                "date": "1988-02-26",
                "id": "1988-013",
                "time": 9.52,
                "site": "",
                "rocket": "Molniya 8K78M",
                "lat": 62.9,
                "lon": 40.5,
                "smc": false,
                "location": "53-y Nauchno-Issledovatelskiy Ispitatelniy Poligon,",
                "emissions": {
                    "BC": 0.8439179645528487,
                    "CO": 7.583947288229512,
                    "CO2": 68.15512312562008,
                    "NOx": 0.28034954692485065,
                    "H2O": 30.246600212912394,
                    "Cly": 0.0,
                    "Al2O3": 0.0
                }
            }
        ],
        "reentries": []
    },
    "1988-03-07": {
        "launches": [
            {
                "date": "1988-03-07",
                "id": "1988-014",
                "time": 12.68,
                "site": "",
                "rocket": "Long March (CZ) 3",
                "lat": 28.2472,
                "lon": 102.0291,
                "smc": false,
                "location": "Xichang Space Center (Songlin), Sichuan, China",
                "emissions": {
                    "BC": 0.9217730900885759,
                    "CO": 1.681752841133059,
                    "CO2": 62.24357906277549,
                    "NOx": 3.1986867978037994,
                    "H2O": 84.51126659148143,
                    "Cly": 0.0,
                    "Al2O3": 0.0
                }
            }
        ],
        "reentries": []
    },
    "1988-03-10": {
        "launches": [
            {
                "date": "1988-03-10",
                "id": "1988-015",
                "time": 10.5,
                "site": "",
                "rocket": "Soyuz-U",
                "lat": 62.9,
                "lon": 40.5,
                "smc": false,
                "location": "53-y Nauchno-Issledovatelskiy Ispitatelniy Poligon,",
                "emissions": {
                    "BC": 1.0935036055473257,
                    "CO": 8.366101332339973,
                    "CO2": 120.33284918913668,
                    "NOx": 0.5917722364437797,
                    "H2O": 50.42076916997716,
                    "Cly": 0.0,
                    "Al2O3": 0.0
                }
            }
        ],
        "reentries": []
    },
    "1988-03-11": {
        "launches": [
            {
                "date": "1988-03-11",
                "id": "1988-016",
                "time": 0.3,
                "site": "",
                "rocket": "Kosmos 11K65M",
                "lat": 62.9,
                "lon": 40.5,
                "smc": false,
                "location": "53-y Nauchno-Issledovatelskiy Ispitatelniy Poligon,",
                "emissions": {
                    "BC": 0.5056838454742355,
                    "CO": 1.2470276250720371,
                    "CO2": 23.339218554519153,
                    "NOx": 1.1672543666128603,
                    "H2O": 32.95033240639436,
                    "Cly": 0.0,
                    "Al2O3": 0.0
                }
            },
            {
                "date": "1988-03-11",
                "id": "1988-017",
                "time": 6.63,
                "site": "",
                "rocket": "Molniya 8K78M",
                "lat": 46.0,
                "lon": 63.0,
                "smc": false,
                "location": "NIIP-5, Baykonur, Kazakstan",
                "emissions": {
                    "BC": 0.8439179645528487,
                    "CO": 7.583947288229512,
                    "CO2": 68.15512312562008,
                    "NOx": 0.28034954692485065,
                    "H2O": 30.246600212912394,
                    "Cly": 0.0,
                    "Al2O3": 0.0
                }
            },
            {
                "date": "1988-03-11",
                "id": "1988-018",
                "time": 23.47,
                "site": "",
                "rocket": "Ariane 3",
                "lat": 5.2333,
                "lon": -52.7517,
                "smc": false,
                "location": "Centre Spatial Guyanais, Kourou, Guyane Francaise",
                "emissions": {
                    "BC": 0.7127990415413408,
                    "CO": 1.7225989851999566,
                    "CO2": 35.60157926470362,
                    "NOx": 1.6253895671463194,
                    "H2O": 49.08720297777771,
                    "Cly": 2.061499217008257,
                    "Al2O3": 3.1160000000000005
                }
            }
        ],
        "reentries": []
    },
    "1988-03-14": {
        "launches": [
            {
                "date": "1988-03-14",
                "id": "1988-019",
                "time": 14.35,
                "site": "",
                "rocket": "Tsiklon-2",
                "lat": 46.0,
                "lon": 63.0,
                "smc": false,
                "location": "NIIP-5, Baykonur, Kazakstan",
                "emissions": {
                    "BC": 0.7329019836116208,
                    "CO": 1.8073526141153948,
                    "CO2": 33.82619343615902,
                    "NOx": 1.6917349611348786,
                    "H2O": 47.755854171416516,
                    "Cly": 0.0,
                    "Al2O3": 0.0
                }
            }
        ],
        "reentries": []
    },
    "1988-03-15": {
        "launches": [
            {
                "date": "1988-03-15",
                "id": "1988-020",
                "time": 18.83,
                "site": "",
                "rocket": "Tsiklon-3",
                "lat": 62.9,
                "lon": 40.5,
                "smc": false,
                "location": "53-y Nauchno-Issledovatelskiy Ispitatelniy Poligon,",
                "emissions": {
                    "BC": 0.6868747189134614,
                    "CO": 1.4627346627604858,
                    "CO2": 41.10299779988749,
                    "NOx": 2.1011553614862866,
                    "H2O": 56.52834032917984,
                    "Cly": 0.0,
                    "Al2O3": 0.0
                }
            }
        ],
        "reentries": []
    },
    "1988-03-17": {
        "launches": [
            {
                "date": "1988-03-17",
                "id": "1988-021",
                "time": 6.72,
                "site": "",
                "rocket": "Vostok 8A92M",
                "lat": 46.0,
                "lon": 63.0,
                "smc": false,
                "location": "NIIP-5, Baykonur, Kazakstan",
                "emissions": {
                    "BC": 0.6219211997837641,
                    "CO": 6.610095793911523,
                    "CO2": 30.247398968117054,
                    "NOx": 0.06535111805879598,
                    "H2O": 15.349094219805028,
                    "Cly": 0.0,
                    "Al2O3": 0.0
                }
            },
            {
                "date": "1988-03-17",
                "id": "1988-022",
                "time": 20.92,
                "site": "",
                "rocket": "Molniya 8K78M",
                "lat": 62.9,
                "lon": 40.5,
                "smc": false,
                "location": "53-y Nauchno-Issledovatelskiy Ispitatelniy Poligon,",
                "emissions": {
                    "BC": 0.8439179645528487,
                    "CO": 7.583947288229512,
                    "CO2": 68.15512312562008,
                    "NOx": 0.28034954692485065,
                    "H2O": 30.246600212912394,
                    "Cly": 0.0,
                    "Al2O3": 0.0
                }
            }
        ],
        "reentries": []
    },
    "1988-03-22": {
        "launches": [
            {
                "date": "1988-03-22",
                "id": "1988-023",
                "time": 14.12,
                "site": "",
                "rocket": "Kosmos 11K65M",
                "lat": 62.9,
                "lon": 40.5,
                "smc": false,
                "location": "53-y Nauchno-Issledovatelskiy Ispitatelniy Poligon,",
                "emissions": {
                    "BC": 0.5056838454742355,
                    "CO": 1.2470276250720371,
                    "CO2": 23.339218554519153,
                    "NOx": 1.1672543666128603,
                    "H2O": 32.95033240639436,
                    "Cly": 0.0,
                    "Al2O3": 0.0
                }
            }
        ],
        "reentries": []
    },
    "1988-03-23": {
        "launches": [
            {
                "date": "1988-03-23",
                "id": "1988-024",
                "time": 21.08,
                "site": "",
                "rocket": "Soyuz-U2",
                "lat": 46.0,
                "lon": 63.0,
                "smc": false,
                "location": "NIIP-5, Baykonur, Kazakstan",
                "emissions": {
                    "BC": 1.0935036055473257,
                    "CO": 8.366101332339973,
                    "CO2": 120.33284918913668,
                    "NOx": 0.5917722364437797,
                    "H2O": 50.42076916997716,
                    "Cly": 0.0,
                    "Al2O3": 0.0
                }
            }
        ],
        "reentries": []
    },
    "1988-03-24": {
        "launches": [
            {
                "date": "1988-03-24",
                "id": "1988-025",
                "time": 14.17,
                "site": "",
                "rocket": "Soyuz-U",
                "lat": 62.9,
                "lon": 40.5,
                "smc": false,
                "location": "53-y Nauchno-Issledovatelskiy Ispitatelniy Poligon,",
                "emissions": {
                    "BC": 1.0935036055473257,
                    "CO": 8.366101332339973,
                    "CO2": 120.33284918913668,
                    "NOx": 0.5917722364437797,
                    "H2O": 50.42076916997716,
                    "Cly": 0.0,
                    "Al2O3": 0.0
                }
            }
        ],
        "reentries": []
    },
    "1988-03-25": {
        "launches": [
            {
                "date": "1988-03-25",
                "id": "1988-026",
                "time": 19.83,
                "site": "",
                "rocket": "Scout G-1",
                "lat": -2.9408,
                "lon": 40.2134,
                "smc": false,
                "location": "San Marco Launch Complex, Formosa Bay, Kenya",
                "emissions": {
                    "BC": 0.059214111177949454,
                    "CO": 0.15826898866675995,
                    "CO2": 6.191311426685871,
                    "NOx": 0.08772794700229372,
                    "H2O": 7.2197193135340045,
                    "Cly": 2.981805131988996,
                    "Al2O3": 4.507062623330614
                }
            }
        ],
        "reentries": []
    },
    "1988-03-30": {
        "launches": [
            {
                "date": "1988-03-30",
                "id": "1988-027",
                "time": 12.0,
                "site": "",
                "rocket": "Soyuz-U",
                "lat": 46.0,
                "lon": 63.0,
                "smc": false,
                "location": "NIIP-5, Baykonur, Kazakstan",
                "emissions": {
                    "BC": 1.0935036055473257,
                    "CO": 8.366101332339973,
                    "CO2": 120.33284918913668,
                    "NOx": 0.5917722364437797,
                    "H2O": 50.42076916997716,
                    "Cly": 0.0,
                    "Al2O3": 0.0
                }
            }
        ],
        "reentries": []
    },
    "1988-03-31": {
        "launches": [
            {
                "date": "1988-03-31",
                "id": "1988-028",
                "time": 4.3,
                "site": "",
                "rocket": "Proton-K/DM",
                "lat": 46.0,
                "lon": 63.0,
                "smc": false,
                "location": "NIIP-5, Baykonur, Kazakstan",
                "emissions": {
                    "BC": 2.1624429718465246,
                    "CO": 4.549336216904315,
                    "CO2": 146.13061133955784,
                    "NOx": 7.56439493696129,
                    "H2O": 199.63896572145242,
                    "Cly": 0.0,
                    "Al2O3": 0.0
                }
            }
        ],
        "reentries": []
    },
    "1988-04-05": {
        "launches": [
            {
                "date": "1988-04-05",
                "id": "1988-029",
                "time": 14.68,
                "site": "",
                "rocket": "Kosmos 11K65M",
                "lat": 62.9,
                "lon": 40.5,
                "smc": false,
                "location": "53-y Nauchno-Issledovatelskiy Ispitatelniy Poligon,",
                "emissions": {
                    "BC": 0.5056838454742355,
                    "CO": 1.2470276250720371,
                    "CO2": 23.339218554519153,
                    "NOx": 1.1672543666128603,
                    "H2O": 32.95033240639436,
                    "Cly": 0.0,
                    "Al2O3": 0.0
                }
            }
        ],
        "reentries": []
    },
    "1988-04-11": {
        "launches": [
            {
                "date": "1988-04-11",
                "id": "1988-030",
                "time": 11.25,
                "site": "",
                "rocket": "Soyuz-U",
                "lat": 62.9,
                "lon": 40.5,
                "smc": false,
                "location": "53-y Nauchno-Issledovatelskiy Ispitatelniy Poligon,",
                "emissions": {
                    "BC": 1.0935036055473257,
                    "CO": 8.366101332339973,
                    "CO2": 120.33284918913668,
                    "NOx": 0.5917722364437797,
                    "H2O": 50.42076916997716,
                    "Cly": 0.0,
                    "Al2O3": 0.0
                }
            }
        ],
        "reentries": []
    },
    "1988-04-14": {
        "launches": [
            {
                "date": "1988-04-14",
                "id": "1988-031",
                "time": 17.0,
                "site": "",
                "rocket": "Soyuz-U",
                "lat": 62.9,
                "lon": 40.5,
                "smc": false,
                "location": "53-y Nauchno-Issledovatelskiy Ispitatelniy Poligon,",
                "emissions": {
                    "BC": 1.0935036055473257,
                    "CO": 8.366101332339973,
                    "CO2": 120.33284918913668,
                    "NOx": 0.5917722364437797,
                    "H2O": 50.42076916997716,
                    "Cly": 0.0,
                    "Al2O3": 0.0
                }
            }
        ],
        "reentries": []
    },
    "1988-04-20": {
        "launches": [
            {
                "date": "1988-04-20",
                "id": "1988-032",
                "time": 5.8,
                "site": "",
                "rocket": "Vostok 8A92M",
                "lat": 46.0,
                "lon": 63.0,
                "smc": false,
                "location": "NIIP-5, Baykonur, Kazakstan",
                "emissions": {
                    "BC": 0.6219211997837641,
                    "CO": 6.610095793911523,
                    "CO2": 30.247398968117054,
                    "NOx": 0.06535111805879598,
                    "H2O": 15.349094219805028,
                    "Cly": 0.0,
                    "Al2O3": 0.0
                }
            }
        ],
        "reentries": []
    },
    "1988-04-26": {
        "launches": [
            {
                "date": "1988-04-26",
                "id": "1988-033",
                "time": 1.95,
                "site": "",
                "rocket": "Scout G-1",
                "lat": 34.63,
                "lon": -120.61,
                "smc": false,
                "location": "South Vandenberg AFB, California",
                "emissions": {
                    "BC": 0.059214111177949454,
                    "CO": 0.15826898866675995,
                    "CO2": 6.191311426685871,
                    "NOx": 0.08772794700229372,
                    "H2O": 7.2197193135340045,
                    "Cly": 2.981805131988996,
                    "Al2O3": 4.507062623330614
                }
            },
            {
                "date": "1988-04-26",
                "id": "1988-034",
                "time": 3.25,
                "site": "",
                "rocket": "Proton-K/DM-2",
                "lat": 46.0,
                "lon": 63.0,
                "smc": false,
                "location": "NIIP-5, Baykonur, Kazakstan",
                "emissions": {
                    "BC": 2.1624429718465246,
                    "CO": 4.549336216904315,
                    "CO2": 146.13061133955784,
                    "NOx": 7.56439493696129,
                    "H2O": 199.63896572145242,
                    "Cly": 0.0,
                    "Al2O3": 0.0
                }
            }
        ],
        "reentries": []
    },
    "1988-04-27": {
        "launches": [
            {
                "date": "1988-04-27",
                "id": "1988-035",
                "time": 9.17,
                "site": "",
                "rocket": "Soyuz-U",
                "lat": 46.0,
                "lon": 63.0,
                "smc": false,
                "location": "NIIP-5, Baykonur, Kazakstan",
                "emissions": {
                    "BC": 1.0935036055473257,
                    "CO": 8.366101332339973,
                    "CO2": 120.33284918913668,
                    "NOx": 0.5917722364437797,
                    "H2O": 50.42076916997716,
                    "Cly": 0.0,
                    "Al2O3": 0.0
                }
            }
        ],
        "reentries": []
    },
    "1988-05-06": {
        "launches": [
            {
                "date": "1988-05-06",
                "id": "1988-036",
                "time": 2.78,
                "site": "",
                "rocket": "Proton-K/DM",
                "lat": 46.0,
                "lon": 63.0,
                "smc": false,
                "location": "NIIP-5, Baykonur, Kazakstan",
                "emissions": {
                    "BC": 2.1624429718465246,
                    "CO": 4.549336216904315,
                    "CO2": 146.13061133955784,
                    "NOx": 7.56439493696129,
                    "H2O": 199.63896572145242,
                    "Cly": 0.0,
                    "Al2O3": 0.0
                }
            }
        ],
        "reentries": []
    },
    "1988-05-12": {
        "launches": [
            {
                "date": "1988-05-12",
                "id": "1988-037",
                "time": 14.65,
                "site": "",
                "rocket": "Soyuz-U",
                "lat": 62.9,
                "lon": 40.5,
                "smc": false,
                "location": "53-y Nauchno-Issledovatelskiy Ispitatelniy Poligon,",
                "emissions": {
                    "BC": 1.0935036055473257,
                    "CO": 8.366101332339973,
                    "CO2": 120.33284918913668,
                    "NOx": 0.5917722364437797,
                    "H2O": 50.42076916997716,
                    "Cly": 0.0,
                    "Al2O3": 0.0
                }
            }
        ],
        "reentries": []
    },
    "1988-05-13": {
        "launches": [
            {
                "date": "1988-05-13",
                "id": "1988-038",
                "time": 0.5,
                "site": "",
                "rocket": "Soyuz-U2",
                "lat": 46.0,
                "lon": 63.0,
                "smc": false,
                "location": "NIIP-5, Baykonur, Kazakstan",
                "emissions": {
                    "BC": 1.0935036055473257,
                    "CO": 8.366101332339973,
                    "CO2": 120.33284918913668,
                    "NOx": 0.5917722364437797,
                    "H2O": 50.42076916997716,
                    "Cly": 0.0,
                    "Al2O3": 0.0
                }
            }
        ],
        "reentries": []
    },
    "1988-05-15": {
        "launches": [
            {
                "date": "1988-05-15",
                "id": "1988-039",
                "time": 9.33,
                "site": "",
                "rocket": "Zenit-2",
                "lat": 46.0,
                "lon": 63.0,
                "smc": false,
                "location": "NIIP-5, Baykonur, Kazakstan",
                "emissions": {
                    "BC": 2.700607972678415,
                    "CO": 18.00724294192844,
                    "CO2": 311.7858082387762,
                    "NOx": 1.5416768501467986,
                    "H2O": 128.46366210822114,
                    "Cly": 0.0,
                    "Al2O3": 0.0
                }
            }
        ],
        "reentries": []
    },
    "1988-05-17": {
        "launches": [
            {
                "date": "1988-05-17",
                "id": "1988-040",
                "time": 23.97,
                "site": "",
                "rocket": "Ariane 2",
                "lat": 5.2333,
                "lon": -52.7517,
                "smc": false,
                "location": "Centre Spatial Guyanais, Kourou, Guyane Francaise",
                "emissions": {
                    "BC": 0.7381911862351096,
                    "CO": 1.3767662995179062,
                    "CO2": 49.09244711092098,
                    "NOx": 2.5212627396383143,
                    "H2O": 66.75833089907933,
                    "Cly": 0.0,
                    "Al2O3": 0.0
                }
            }
        ],
        "reentries": []
    },
    "1988-05-18": {
        "launches": [
            {
                "date": "1988-05-18",
                "id": "1988-041",
                "time": 10.5,
                "site": "",
                "rocket": "Soyuz-U",
                "lat": 46.0,
                "lon": 63.0,
                "smc": false,
                "location": "NIIP-5, Baykonur, Kazakstan",
                "emissions": {
                    "BC": 1.0935036055473257,
                    "CO": 8.366101332339973,
                    "CO2": 120.33284918913668,
                    "NOx": 0.5917722364437797,
                    "H2O": 50.42076916997716,
                    "Cly": 0.0,
                    "Al2O3": 0.0
                }
            }
        ],
        "reentries": []
    },
    "1988-05-19": {
        "launches": [
            {
                "date": "1988-05-19",
                "id": "1988-042",
                "time": 9.25,
                "site": "",
                "rocket": "Soyuz-U",
                "lat": 46.0,
                "lon": 63.0,
                "smc": false,
                "location": "NIIP-5, Baykonur, Kazakstan",
                "emissions": {
                    "BC": 1.0935036055473257,
                    "CO": 8.366101332339973,
                    "CO2": 120.33284918913668,
                    "NOx": 0.5917722364437797,
                    "H2O": 50.42076916997716,
                    "Cly": 0.0,
                    "Al2O3": 0.0
                }
            }
        ],
        "reentries": []
    },
    "1988-05-21": {
        "launches": [
            {
                "date": "1988-05-21",
                "id": "1988-043",
                "time": 17.95,
                "site": "",
                "rocket": "Proton-K/DM-2",
                "lat": 46.0,
                "lon": 63.0,
                "smc": false,
                "location": "NIIP-5, Baykonur, Kazakstan",
                "emissions": {
                    "BC": 2.1624429718465246,
                    "CO": 4.549336216904315,
                    "CO2": 146.13061133955784,
                    "NOx": 7.56439493696129,
                    "H2O": 199.63896572145242,
                    "Cly": 0.0,
                    "Al2O3": 0.0
                }
            }
        ],
        "reentries": []
    },
    "1988-05-26": {
        "launches": [
            {
                "date": "1988-05-26",
                "id": "1988-044",
                "time": 15.45,
                "site": "",
                "rocket": "Molniya 8K78M",
                "lat": 62.9,
                "lon": 40.5,
                "smc": false,
                "location": "53-y Nauchno-Issledovatelskiy Ispitatelniy Poligon,",
                "emissions": {
                    "BC": 0.8439179645528487,
                    "CO": 7.583947288229512,
                    "CO2": 68.15512312562008,
                    "NOx": 0.28034954692485065,
                    "H2O": 30.246600212912394,
                    "Cly": 0.0,
                    "Al2O3": 0.0
                }
            }
        ],
        "reentries": []
    },
    "1988-05-28": {
        "launches": [
            {
                "date": "1988-05-28",
                "id": "1988-045",
                "time": 2.82,
                "site": "",
                "rocket": "Tsiklon-2",
                "lat": 46.0,
                "lon": 63.0,
                "smc": false,
                "location": "NIIP-5, Baykonur, Kazakstan",
                "emissions": {
                    "BC": 0.7329019836116208,
                    "CO": 1.8073526141153948,
                    "CO2": 33.82619343615902,
                    "NOx": 1.6917349611348786,
                    "H2O": 47.755854171416516,
                    "Cly": 0.0,
                    "Al2O3": 0.0
                }
            }
        ],
        "reentries": []
    },
    "1988-05-30": {
        "launches": [
            {
                "date": "1988-05-30",
                "id": "1988-046",
                "time": 8.0,
                "site": "",
                "rocket": "Tsiklon-3",
                "lat": 62.9,
                "lon": 40.5,
                "smc": false,
                "location": "53-y Nauchno-Issledovatelskiy Ispitatelniy Poligon,",
                "emissions": {
                    "BC": 0.6868747189134614,
                    "CO": 1.4627346627604858,
                    "CO2": 41.10299779988749,
                    "NOx": 2.1011553614862866,
                    "H2O": 56.52834032917984,
                    "Cly": 0.0,
                    "Al2O3": 0.0
                }
            }
        ],
        "reentries": []
    },
    "1988-05-31": {
        "launches": [
            {
                "date": "1988-05-31",
                "id": "1988-047",
                "time": 7.75,
                "site": "",
                "rocket": "Soyuz-U",
                "lat": 62.9,
                "lon": 40.5,
                "smc": false,
                "location": "53-y Nauchno-Issledovatelskiy Ispitatelniy Poligon,",
                "emissions": {
                    "BC": 1.0935036055473257,
                    "CO": 8.366101332339973,
                    "CO2": 120.33284918913668,
                    "NOx": 0.5917722364437797,
                    "H2O": 50.42076916997716,
                    "Cly": 0.0,
                    "Al2O3": 0.0
                }
            }
        ],
        "reentries": []
    },
    "1988-06-07": {
        "launches": [
            {
                "date": "1988-06-07",
                "id": "1988-048",
                "time": 14.05,
                "site": "",
                "rocket": "Soyuz-U2",
                "lat": 46.0,
                "lon": 63.0,
                "smc": false,
                "location": "NIIP-5, Baykonur, Kazakstan",
                "emissions": {
                    "BC": 1.0935036055473257,
                    "CO": 8.366101332339973,
                    "CO2": 120.33284918913668,
                    "NOx": 0.5917722364437797,
                    "H2O": 50.42076916997716,
                    "Cly": 0.0,
                    "Al2O3": 0.0
                }
            }
        ],
        "reentries": []
    },
    "1988-06-11": {
        "launches": [
            {
                "date": "1988-06-11",
                "id": "1988-049",
                "time": 10.0,
                "site": "",
                "rocket": "Soyuz-U",
                "lat": 46.0,
                "lon": 63.0,
                "smc": false,
                "location": "NIIP-5, Baykonur, Kazakstan",
                "emissions": {
                    "BC": 1.0935036055473257,
                    "CO": 8.366101332339973,
                    "CO2": 120.33284918913668,
                    "NOx": 0.5917722364437797,
                    "H2O": 50.42076916997716,
                    "Cly": 0.0,
                    "Al2O3": 0.0
                }
            }
        ],
        "reentries": []
    },
    "1988-06-14": {
        "launches": [
            {
                "date": "1988-06-14",
                "id": "1988-050",
                "time": 3.3,
                "site": "",
                "rocket": "Tsiklon-3",
                "lat": 62.9,
                "lon": 40.5,
                "smc": false,
                "location": "53-y Nauchno-Issledovatelskiy Ispitatelniy Poligon,",
                "emissions": {
                    "BC": 0.6868747189134614,
                    "CO": 1.4627346627604858,
                    "CO2": 41.10299779988749,
                    "NOx": 2.1011553614862866,
                    "H2O": 56.52834032917984,
                    "Cly": 0.0,
                    "Al2O3": 0.0
                }
            }
        ],
        "reentries": []
    },
    "1988-06-15": {
        "launches": [
            {
                "date": "1988-06-15",
                "id": "1988-051",
                "time": 11.32,
                "site": "",
                "rocket": "Ariane 44LP",
                "lat": 5.2333,
                "lon": -52.7517,
                "smc": false,
                "location": "Centre Spatial Guyanais, Kourou, Guyane Francaise",
                "emissions": {
                    "BC": 1.091537267852126,
                    "CO": 2.656575886197079,
                    "CO2": 53.081778242641334,
                    "NOx": 2.4996192907592674,
                    "H2O": 73.76576560863481,
                    "Cly": 2.061499217008257,
                    "Al2O3": 3.1160000000000005
                }
            }
        ],
        "reentries": []
    },
    "1988-06-16": {
        "launches": [
            {
                "date": "1988-06-16",
                "id": "1988-052",
                "time": 6.9,
                "site": "",
                "rocket": "Scout G-1",
                "lat": 34.63,
                "lon": -120.61,
                "smc": false,
                "location": "South Vandenberg AFB, California",
                "emissions": {
                    "BC": 0.059214111177949454,
                    "CO": 0.15826898866675995,
                    "CO2": 6.191311426685871,
                    "NOx": 0.08772794700229372,
                    "H2O": 7.2197193135340045,
                    "Cly": 2.981805131988996,
                    "Al2O3": 4.507062623330614
                }
            }
        ],
        "reentries": []
    },
    "1988-06-21": {
        "launches": [
            {
                "date": "1988-06-21",
                "id": "1988-053",
                "time": 16.43,
                "site": "",
                "rocket": "Kosmos 11K65M",
                "lat": 62.9,
                "lon": 40.5,
                "smc": false,
                "location": "53-y Nauchno-Issledovatelskiy Ispitatelniy Poligon,",
                "emissions": {
                    "BC": 0.5056838454742355,
                    "CO": 1.2470276250720371,
                    "CO2": 23.339218554519153,
                    "NOx": 1.1672543666128603,
                    "H2O": 32.95033240639436,
                    "Cly": 0.0,
                    "Al2O3": 0.0
                }
            }
        ],
        "reentries": []
    },
    "1988-06-22": {
        "launches": [
            {
                "date": "1988-06-22",
                "id": "1988-054",
                "time": 13.0,
                "site": "",
                "rocket": "Soyuz-U",
                "lat": 46.0,
                "lon": 63.0,
                "smc": false,
                "location": "NIIP-5, Baykonur, Kazakstan",
                "emissions": {
                    "BC": 1.0935036055473257,
                    "CO": 8.366101332339973,
                    "CO2": 120.33284918913668,
                    "NOx": 0.5917722364437797,
                    "H2O": 50.42076916997716,
                    "Cly": 0.0,
                    "Al2O3": 0.0
                }
            }
        ],
        "reentries": []
    },
    "1988-06-23": {
        "launches": [
            {
                "date": "1988-06-23",
                "id": "1988-055",
                "time": 7.75,
                "site": "",
                "rocket": "Soyuz-U",
                "lat": 62.9,
                "lon": 40.5,
                "smc": false,
                "location": "53-y Nauchno-Issledovatelskiy Ispitatelniy Poligon,",
                "emissions": {
                    "BC": 1.0935036055473257,
                    "CO": 8.366101332339973,
                    "CO2": 120.33284918913668,
                    "NOx": 0.5917722364437797,
                    "H2O": 50.42076916997716,
                    "Cly": 0.0,
                    "Al2O3": 0.0
                }
            }
        ],
        "reentries": []
    },
    "1988-07-05": {
        "launches": [
            {
                "date": "1988-07-05",
                "id": "1988-056",
                "time": 9.75,
                "site": "",
                "rocket": "Tsiklon-3",
                "lat": 62.9,
                "lon": 40.5,
                "smc": false,
                "location": "53-y Nauchno-Issledovatelskiy Ispitatelniy Poligon,",
                "emissions": {
                    "BC": 0.6868747189134614,
                    "CO": 1.4627346627604858,
                    "CO2": 41.10299779988749,
                    "NOx": 2.1011553614862866,
                    "H2O": 56.52834032917984,
                    "Cly": 0.0,
                    "Al2O3": 0.0
                }
            }
        ],
        "reentries": []
    },
    "1988-07-07": {
        "launches": [
            {
                "date": "1988-07-07",
                "id": "1988-057",
                "time": 8.08,
                "site": "",
                "rocket": "Soyuz-U",
                "lat": 62.9,
                "lon": 40.5,
                "smc": false,
                "location": "53-y Nauchno-Issledovatelskiy Ispitatelniy Poligon,",
                "emissions": {
                    "BC": 1.0935036055473257,
                    "CO": 8.366101332339973,
                    "CO2": 120.33284918913668,
                    "NOx": 0.5917722364437797,
                    "H2O": 50.42076916997716,
                    "Cly": 0.0,
                    "Al2O3": 0.0
                }
            },
            {
                "date": "1988-07-07",
                "id": "1988-058",
                "time": 17.63,
                "site": "",
                "rocket": "Proton-K/D-2",
                "lat": 46.0,
                "lon": 63.0,
                "smc": false,
                "location": "NIIP-5, Baykonur, Kazakstan",
                "emissions": {
                    "BC": 2.1624429718465246,
                    "CO": 4.549336216904315,
                    "CO2": 146.13061133955784,
                    "NOx": 7.56439493696129,
                    "H2O": 199.63896572145242,
                    "Cly": 0.0,
                    "Al2O3": 0.0
                }
            }
        ],
        "reentries": []
    },
    "1988-07-09": {
        "launches": [],
        "reentries": []
    },
    "1988-07-12": {
        "launches": [
            {
                "date": "1988-07-12",
                "id": "1988-059",
                "time": 17.02,
                "site": "",
                "rocket": "Proton-K/D-2",
                "lat": 46.0,
                "lon": 63.0,
                "smc": false,
                "location": "NIIP-5, Baykonur, Kazakstan",
                "emissions": {
                    "BC": 2.1624429718465246,
                    "CO": 4.549336216904315,
                    "CO2": 146.13061133955784,
                    "NOx": 7.56439493696129,
                    "H2O": 199.63896572145242,
                    "Cly": 0.0,
                    "Al2O3": 0.0
                }
            }
        ],
        "reentries": []
    },
    "1988-07-13": {
        "launches": [],
        "reentries": []
    },
    "1988-07-14": {
        "launches": [
            {
                "date": "1988-07-14",
                "id": "1988-060",
                "time": 11.67,
                "site": "",
                "rocket": "Kosmos 11K65M",
                "lat": 62.9,
                "lon": 40.5,
                "smc": false,
                "location": "53-y Nauchno-Issledovatelskiy Ispitatelniy Poligon,",
                "emissions": {
                    "BC": 0.5056838454742355,
                    "CO": 1.2470276250720371,
                    "CO2": 23.339218554519153,
                    "NOx": 1.1672543666128603,
                    "H2O": 32.95033240639436,
                    "Cly": 0.0,
                    "Al2O3": 0.0
                }
            }
        ],
        "reentries": []
    },
    "1988-07-18": {
        "launches": [
            {
                "date": "1988-07-18",
                "id": "1988-061",
                "time": 21.22,
                "site": "",
                "rocket": "Soyuz-U2",
                "lat": 46.0,
                "lon": 63.0,
                "smc": false,
                "location": "NIIP-5, Baykonur, Kazakstan",
                "emissions": {
                    "BC": 1.0935036055473257,
                    "CO": 8.366101332339973,
                    "CO2": 120.33284918913668,
                    "NOx": 0.5917722364437797,
                    "H2O": 50.42076916997716,
                    "Cly": 0.0,
                    "Al2O3": 0.0
                }
            },
            {
                "date": "1988-07-18",
                "id": "1988-062",
                "time": 22.47,
                "site": "",
                "rocket": "Kosmos 11K65M",
                "lat": 62.9,
                "lon": 40.5,
                "smc": false,
                "location": "53-y Nauchno-Issledovatelskiy Ispitatelniy Poligon,",
                "emissions": {
                    "BC": 0.5056838454742355,
                    "CO": 1.2470276250720371,
                    "CO2": 23.339218554519153,
                    "NOx": 1.1672543666128603,
                    "H2O": 32.95033240639436,
                    "Cly": 0.0,
                    "Al2O3": 0.0
                }
            }
        ],
        "reentries": []
    },
    "1988-07-21": {
        "launches": [
            {
                "date": "1988-07-21",
                "id": "1988-063",
                "time": 23.2,
                "site": "",
                "rocket": "Ariane 3",
                "lat": 5.2333,
                "lon": -52.7517,
                "smc": false,
                "location": "Centre Spatial Guyanais, Kourou, Guyane Francaise",
                "emissions": {
                    "BC": 0.7127990415413408,
                    "CO": 1.7225989851999566,
                    "CO2": 35.60157926470362,
                    "NOx": 1.6253895671463194,
                    "H2O": 49.08720297777771,
                    "Cly": 2.061499217008257,
                    "Al2O3": 3.1160000000000005
                }
            }
        ],
        "reentries": []
    },
    "1988-07-26": {
        "launches": [
            {
                "date": "1988-07-26",
                "id": "1988-064",
                "time": 5.02,
                "site": "",
                "rocket": "Tsiklon-3",
                "lat": 62.9,
                "lon": 40.5,
                "smc": false,
                "location": "53-y Nauchno-Issledovatelskiy Ispitatelniy Poligon,",
                "emissions": {
                    "BC": 0.6868747189134614,
                    "CO": 1.4627346627604858,
                    "CO2": 41.10299779988749,
                    "NOx": 2.1011553614862866,
                    "H2O": 56.52834032917984,
                    "Cly": 0.0,
                    "Al2O3": 0.0
                }
            }
        ],
        "reentries": []
    },
    "1988-07-27": {
        "launches": [],
        "reentries": []
    },
    "1988-07-28": {
        "launches": [
            {
                "date": "1988-07-28",
                "id": "1988-065",
                "time": 11.33,
                "site": "",
                "rocket": "Kosmos 11K65M",
                "lat": 62.9,
                "lon": 40.5,
                "smc": false,
                "location": "53-y Nauchno-Issledovatelskiy Ispitatelniy Poligon,",
                "emissions": {
                    "BC": 0.5056838454742355,
                    "CO": 1.2470276250720371,
                    "CO2": 23.339218554519153,
                    "NOx": 1.1672543666128603,
                    "H2O": 32.95033240639436,
                    "Cly": 0.0,
                    "Al2O3": 0.0
                }
            }
        ],
        "reentries": []
    },
    "1988-08-01": {
        "launches": [
            {
                "date": "1988-08-01",
                "id": "1988-066",
                "time": 21.07,
                "site": "",
                "rocket": "Proton-K/DM-2",
                "lat": 46.0,
                "lon": 63.0,
                "smc": false,
                "location": "NIIP-5, Baykonur, Kazakstan",
                "emissions": {
                    "BC": 2.1624429718465246,
                    "CO": 4.549336216904315,
                    "CO2": 146.13061133955784,
                    "NOx": 7.56439493696129,
                    "H2O": 199.63896572145242,
                    "Cly": 0.0,
                    "Al2O3": 0.0
                }
            }
        ],
        "reentries": []
    },
    "1988-08-05": {
        "launches": [
            {
                "date": "1988-08-05",
                "id": "1988-067",
                "time": 7.47,
                "site": "",
                "rocket": "Long March (CZ) 2C",
                "lat": 41.31,
                "lon": 100.31,
                "smc": false,
                "location": "Jiuquan Space Center, Nei Monggol Zizhiqu, China",
                "emissions": {
                    "BC": 1.090086825324316,
                    "CO": 5.790095529042271,
                    "CO2": 200.93677911524193,
                    "NOx": 1.1816368255070118,
                    "H2O": 79.33968149277139,
                    "Cly": 0.0,
                    "Al2O3": 0.0
                }
            }
        ],
        "reentries": []
    },
    "1988-08-08": {
        "launches": [
            {
                "date": "1988-08-08",
                "id": "1988-068",
                "time": 9.42,
                "site": "",
                "rocket": "Soyuz-U",
                "lat": 46.0,
                "lon": 63.0,
                "smc": false,
                "location": "NIIP-5, Baykonur, Kazakstan",
                "emissions": {
                    "BC": 1.0935036055473257,
                    "CO": 8.366101332339973,
                    "CO2": 120.33284918913668,
                    "NOx": 0.5917722364437797,
                    "H2O": 50.42076916997716,
                    "Cly": 0.0,
                    "Al2O3": 0.0
                }
            }
        ],
        "reentries": []
    },
    "1988-08-12": {
        "launches": [
            {
                "date": "1988-08-12",
                "id": "1988-069",
                "time": 12.88,
                "site": "",
                "rocket": "Molniya 8K78M",
                "lat": 62.9,
                "lon": 40.5,
                "smc": false,
                "location": "53-y Nauchno-Issledovatelskiy Ispitatelniy Poligon,",
                "emissions": {
                    "BC": 0.8439179645528487,
                    "CO": 7.583947288229512,
                    "CO2": 68.15512312562008,
                    "NOx": 0.28034954692485065,
                    "H2O": 30.246600212912394,
                    "Cly": 0.0,
                    "Al2O3": 0.0
                }
            }
        ],
        "reentries": []
    },
    "1988-08-16": {
        "launches": [
            {
                "date": "1988-08-16",
                "id": "1988-070",
                "time": 13.0,
                "site": "",
                "rocket": "Soyuz-U",
                "lat": 46.0,
                "lon": 63.0,
                "smc": false,
                "location": "NIIP-5, Baykonur, Kazakstan",
                "emissions": {
                    "BC": 1.0935036055473257,
                    "CO": 8.366101332339973,
                    "CO2": 120.33284918913668,
                    "NOx": 0.5917722364437797,
                    "H2O": 50.42076916997716,
                    "Cly": 0.0,
                    "Al2O3": 0.0
                }
            }
        ],
        "reentries": []
    },
    "1988-08-18": {
        "launches": [
            {
                "date": "1988-08-18",
                "id": "1988-071",
                "time": 19.87,
                "site": "",
                "rocket": "Proton-K/DM-2",
                "lat": 46.0,
                "lon": 63.0,
                "smc": false,
                "location": "NIIP-5, Baykonur, Kazakstan",
                "emissions": {
                    "BC": 2.1624429718465246,
                    "CO": 4.549336216904315,
                    "CO2": 146.13061133955784,
                    "NOx": 7.56439493696129,
                    "H2O": 199.63896572145242,
                    "Cly": 0.0,
                    "Al2O3": 0.0
                }
            }
        ],
        "reentries": []
    },
    "1988-08-23": {
        "launches": [
            {
                "date": "1988-08-23",
                "id": "1988-072",
                "time": 9.33,
                "site": "",
                "rocket": "Soyuz-U",
                "lat": 46.0,
                "lon": 63.0,
                "smc": false,
                "location": "NIIP-5, Baykonur, Kazakstan",
                "emissions": {
                    "BC": 1.0935036055473257,
                    "CO": 8.366101332339973,
                    "CO2": 120.33284918913668,
                    "NOx": 0.5917722364437797,
                    "H2O": 50.42076916997716,
                    "Cly": 0.0,
                    "Al2O3": 0.0
                }
            },
            {
                "date": "1988-08-23",
                "id": "1988-073",
                "time": 11.25,
                "site": "",
                "rocket": "Soyuz-U",
                "lat": 62.9,
                "lon": 40.5,
                "smc": false,
                "location": "53-y Nauchno-Issledovatelskiy Ispitatelniy Poligon,",
                "emissions": {
                    "BC": 1.0935036055473257,
                    "CO": 8.366101332339973,
                    "CO2": 120.33284918913668,
                    "NOx": 0.5917722364437797,
                    "H2O": 50.42076916997716,
                    "Cly": 0.0,
                    "Al2O3": 0.0
                }
            }
        ],
        "reentries": []
    },
    "1988-08-25": {
        "launches": [
            {
                "date": "1988-08-25",
                "id": "1988-074",
                "time": 6.98,
                "site": "",
                "rocket": "Scout G-1",
                "lat": 34.63,
                "lon": -120.61,
                "smc": false,
                "location": "South Vandenberg AFB, California",
                "emissions": {
                    "BC": 0.059214111177949454,
                    "CO": 0.15826898866675995,
                    "CO2": 6.191311426685871,
                    "NOx": 0.08772794700229372,
                    "H2O": 7.2197193135340045,
                    "Cly": 2.981805131988996,
                    "Al2O3": 4.507062623330614
                }
            }
        ],
        "reentries": []
    },
    "1988-08-29": {
        "launches": [
            {
                "date": "1988-08-29",
                "id": "1988-075",
                "time": 4.38,
                "site": "",
                "rocket": "Soyuz-U2",
                "lat": 46.0,
                "lon": 63.0,
                "smc": false,
                "location": "NIIP-5, Baykonur, Kazakstan",
                "emissions": {
                    "BC": 1.0935036055473257,
                    "CO": 8.366101332339973,
                    "CO2": 120.33284918913668,
                    "NOx": 0.5917722364437797,
                    "H2O": 50.42076916997716,
                    "Cly": 0.0,
                    "Al2O3": 0.0
                }
            }
        ],
        "reentries": []
    },
    "1988-08-30": {
        "launches": [
            {
                "date": "1988-08-30",
                "id": "1988-076",
                "time": 14.23,
                "site": "",
                "rocket": "Molniya 8K78M",
                "lat": 62.9,
                "lon": 40.5,
                "smc": false,
                "location": "53-y Nauchno-Issledovatelskiy Ispitatelniy Poligon,",
                "emissions": {
                    "BC": 0.8439179645528487,
                    "CO": 7.583947288229512,
                    "CO2": 68.15512312562008,
                    "NOx": 0.28034954692485065,
                    "H2O": 30.246600212912394,
                    "Cly": 0.0,
                    "Al2O3": 0.0
                }
            }
        ],
        "reentries": []
    },
    "1988-09-02": {
        "launches": [
            {
                "date": "1988-09-02",
                "id": "1988-077",
                "time": 12.08,
                "site": "",
                "rocket": "Titan 34D/Transtage",
                "lat": 28.46,
                "lon": -80.54,
                "smc": false,
                "location": "Cape Canaveral Air Station, Florida",
                "emissions": {
                    "BC": 1.3128877154023115,
                    "CO": 2.458480850670174,
                    "CO2": 120.46376768495271,
                    "NOx": 2.5888265001011206,
                    "H2O": 144.04455084546024,
                    "Cly": 45.656782658793404,
                    "Al2O3": 69.01119999999997
                }
            }
        ],
        "reentries": []
    },
    "1988-09-05": {
        "launches": [
            {
                "date": "1988-09-05",
                "id": "1988-078",
                "time": 9.42,
                "site": "",
                "rocket": "Titan II SLV",
                "lat": 34.63,
                "lon": -120.61,
                "smc": false,
                "location": "South Vandenberg AFB, California",
                "emissions": {
                    "BC": 0.7285798994622688,
                    "CO": 1.7966942583455485,
                    "CO2": 33.62671293569305,
                    "NOx": 1.681758428086906,
                    "H2O": 47.47422739871226,
                    "Cly": 0.0,
                    "Al2O3": 0.0
                }
            }
        ],
        "reentries": []
    },
    "1988-09-06": {
        "launches": [
            {
                "date": "1988-09-06",
                "id": "1988-079",
                "time": 7.5,
                "site": "",
                "rocket": "Soyuz-U",
                "lat": 62.9,
                "lon": 40.5,
                "smc": false,
                "location": "53-y Nauchno-Issledovatelskiy Ispitatelniy Poligon,",
                "emissions": {
                    "BC": 1.0935036055473257,
                    "CO": 8.366101332339973,
                    "CO2": 120.33284918913668,
                    "NOx": 0.5917722364437797,
                    "H2O": 50.42076916997716,
                    "Cly": 0.0,
                    "Al2O3": 0.0
                }
            },
            {
                "date": "1988-09-06",
                "id": "1988-080",
                "time": 20.5,
                "site": "",
                "rocket": "Long March (CZ) 4",
                "lat": 37.5,
                "lon": 112.6,
                "smc": false,
                "location": "Taiyuan weixing fashe zhongxin",
                "emissions": {
                    "BC": 0.8858861853648333,
                    "CO": 1.5718683100407764,
                    "CO2": 60.93903416738146,
                    "NOx": 3.1340032606211388,
                    "H2O": 82.58727826224336,
                    "Cly": 0.0,
                    "Al2O3": 0.0
                }
            }
        ],
        "reentries": []
    },
    "1988-09-08": {
        "launches": [
            {
                "date": "1988-09-08",
                "id": "1988-081",
                "time": 23.0,
                "site": "",
                "rocket": "Ariane 3",
                "lat": 5.2333,
                "lon": -52.7517,
                "smc": false,
                "location": "Centre Spatial Guyanais, Kourou, Guyane Francaise",
                "emissions": {
                    "BC": 0.7127990415413408,
                    "CO": 1.7225989851999566,
                    "CO2": 35.60157926470362,
                    "NOx": 1.6253895671463194,
                    "H2O": 49.08720297777771,
                    "Cly": 2.061499217008257,
                    "Al2O3": 3.1160000000000005
                }
            }
        ],
        "reentries": []
    },
    "1988-09-09": {
        "launches": [
            {
                "date": "1988-09-09",
                "id": "1988-082",
                "time": 10.67,
                "site": "",
                "rocket": "Soyuz-U",
                "lat": 62.9,
                "lon": 40.5,
                "smc": false,
                "location": "53-y Nauchno-Issledovatelskiy Ispitatelniy Poligon,",
                "emissions": {
                    "BC": 1.0935036055473257,
                    "CO": 8.366101332339973,
                    "CO2": 120.33284918913668,
                    "NOx": 0.5917722364437797,
                    "H2O": 50.42076916997716,
                    "Cly": 0.0,
                    "Al2O3": 0.0
                }
            },
            {
                "date": "1988-09-09",
                "id": "1988-083",
                "time": 23.55,
                "site": "",
                "rocket": "Soyuz-U2",
                "lat": 46.0,
                "lon": 63.0,
                "smc": false,
                "location": "NIIP-5, Baykonur, Kazakstan",
                "emissions": {
                    "BC": 1.0935036055473257,
                    "CO": 8.366101332339973,
                    "CO2": 120.33284918913668,
                    "NOx": 0.5917722364437797,
                    "H2O": 50.42076916997716,
                    "Cly": 0.0,
                    "Al2O3": 0.0
                }
            }
        ],
        "reentries": []
    },
    "1988-09-15": {
        "launches": [
            {
                "date": "1988-09-15",
                "id": "1988-084",
                "time": 15.0,
                "site": "",
                "rocket": "Soyuz-U",
                "lat": 62.9,
                "lon": 40.5,
                "smc": false,
                "location": "53-y Nauchno-Issledovatelskiy Ispitatelniy Poligon,",
                "emissions": {
                    "BC": 1.0935036055473257,
                    "CO": 8.366101332339973,
                    "CO2": 120.33284918913668,
                    "NOx": 0.5917722364437797,
                    "H2O": 50.42076916997716,
                    "Cly": 0.0,
                    "Al2O3": 0.0
                }
            }
        ],
        "reentries": []
    },
    "1988-09-16": {
        "launches": [
            {
                "date": "1988-09-16",
                "id": "1988-085",
                "time": 2.0,
                "site": "",
                "rocket": "Proton-K/DM-2",
                "lat": 46.0,
                "lon": 63.0,
                "smc": false,
                "location": "NIIP-5, Baykonur, Kazakstan",
                "emissions": {
                    "BC": 2.1624429718465246,
                    "CO": 4.549336216904315,
                    "CO2": 146.13061133955784,
                    "NOx": 7.56439493696129,
                    "H2O": 199.63896572145242,
                    "Cly": 0.0,
                    "Al2O3": 0.0
                }
            },
            {
                "date": "1988-09-16",
                "id": "1988-086",
                "time": 9.98,
                "site": "",
                "rocket": "H-1",
                "lat": 30.4,
                "lon": 130.97,
                "smc": false,
                "location": "Tanegashima Space Center, Tanegashima, Nippon",
                "emissions": {
                    "BC": 0.5309432643851177,
                    "CO": 3.4727315188310923,
                    "CO2": 61.37123038799858,
                    "NOx": 0.31854308264185827,
                    "H2O": 26.44057239047615,
                    "Cly": 0.7453947168866696,
                    "Al2O3": 1.1266800000000001
                }
            }
        ],
        "reentries": []
    },
    "1988-09-19": {
        "launches": [
            {
                "date": "1988-09-19",
                "id": "1988-087",
                "time": 9.52,
                "site": "",
                "rocket": "Shavit",
                "lat": 31.9,
                "lon": 34.7,
                "smc": false,
                "location": "Israeli Air Force Test Range, Palmachim Beach, Israel",
                "emissions": {
                    "BC": 0.06813364071141553,
                    "CO": 0.27481816493286015,
                    "CO2": 4.417484599779877,
                    "NOx": 0.05320038953264454,
                    "H2O": 5.43642064560399,
                    "Cly": 2.2452879077399364,
                    "Al2O3": 3.3938006773439127
                }
            }
        ],
        "reentries": []
    },
    "1988-09-22": {
        "launches": [
            {
                "date": "1988-09-22",
                "id": "1988-088",
                "time": 10.33,
                "site": "",
                "rocket": "Soyuz-U-PVB",
                "lat": 62.9,
                "lon": 40.5,
                "smc": false,
                "location": "53-y Nauchno-Issledovatelskiy Ispitatelniy Poligon,",
                "emissions": {
                    "BC": 1.0720628966110188,
                    "CO": 8.246379552389595,
                    "CO2": 123.3954888630108,
                    "NOx": 0.622384918322759,
                    "H2O": 51.50661211767427,
                    "Cly": 0.0,
                    "Al2O3": 0.0
                }
            }
        ],
        "reentries": []
    },
    "1988-09-24": {
        "launches": [
            {
                "date": "1988-09-24",
                "id": "1988-089",
                "time": 10.03,
                "site": "",
                "rocket": "Atlas E",
                "lat": 34.63,
                "lon": -120.61,
                "smc": false,
                "location": "South Vandenberg AFB, California",
                "emissions": {
                    "BC": 0.715773602717771,
                    "CO": 4.772669445530476,
                    "CO2": 82.63622617465901,
                    "NOx": 0.4086085816305048,
                    "H2O": 34.04822142857137,
                    "Cly": 0.0,
                    "Al2O3": 0.0
                }
            }
        ],
        "reentries": []
    },
    "1988-09-29": {
        "launches": [
            {
                "date": "1988-09-29",
                "id": "1988-090",
                "time": 9.12,
                "site": "",
                "rocket": "Molniya 8K78M",
                "lat": 62.9,
                "lon": 40.5,
                "smc": false,
                "location": "53-y Nauchno-Issledovatelskiy Ispitatelniy Poligon,",
                "emissions": {
                    "BC": 0.8439179645528487,
                    "CO": 7.583947288229512,
                    "CO2": 68.15512312562008,
                    "NOx": 0.28034954692485065,
                    "H2O": 30.246600212912394,
                    "Cly": 0.0,
                    "Al2O3": 0.0
                }
            },
            {
                "date": "1988-09-29",
                "id": "1988-091",
                "time": 15.62,
                "site": "",
                "rocket": "Space Shuttle",
                "lat": 28.6083,
                "lon": -80.6041,
                "smc": false,
                "location": "NASA John F. Kennedy Space Center, Florida",
                "emissions": {
                    "BC": 1.9945134389312427,
                    "CO": 3.0535543664846507,
                    "CO2": 230.47350418889712,
                    "NOx": 3.297110619897022,
                    "H2O": 537.9217532925974,
                    "Cly": 108.93395922362025,
                    "Al2O3": 164.65599999999995
                }
            }
        ],
        "reentries": []
    },
    "1988-10-03": {
        "launches": [
            {
                "date": "1988-10-03",
                "id": "1988-092",
                "time": 22.38,
                "site": "",
                "rocket": "Molniya 8K78M",
                "lat": 62.9,
                "lon": 40.5,
                "smc": false,
                "location": "53-y Nauchno-Issledovatelskiy Ispitatelniy Poligon,",
                "emissions": {
                    "BC": 0.8439179645528487,
                    "CO": 7.583947288229512,
                    "CO2": 68.15512312562008,
                    "NOx": 0.28034954692485065,
                    "H2O": 30.246600212912394,
                    "Cly": 0.0,
                    "Al2O3": 0.0
                }
            }
        ],
        "reentries": []
    },
    "1988-10-11": {
        "launches": [
            {
                "date": "1988-10-11",
                "id": "1988-093",
                "time": 8.03,
                "site": "",
                "rocket": "Tsiklon-3",
                "lat": 62.9,
                "lon": 40.5,
                "smc": false,
                "location": "53-y Nauchno-Issledovatelskiy Ispitatelniy Poligon,",
                "emissions": {
                    "BC": 0.6868747189134614,
                    "CO": 1.4627346627604858,
                    "CO2": 41.10299779988749,
                    "NOx": 2.1011553614862866,
                    "H2O": 56.52834032917984,
                    "Cly": 0.0,
                    "Al2O3": 0.0
                }
            }
        ],
        "reentries": []
    },
    "1988-10-13": {
        "launches": [
            {
                "date": "1988-10-13",
                "id": "1988-094",
                "time": 11.32,
                "site": "",
                "rocket": "Soyuz-U",
                "lat": 62.9,
                "lon": 40.5,
                "smc": false,
                "location": "53-y Nauchno-Issledovatelskiy Ispitatelniy Poligon,",
                "emissions": {
                    "BC": 1.0935036055473257,
                    "CO": 8.366101332339973,
                    "CO2": 120.33284918913668,
                    "NOx": 0.5917722364437797,
                    "H2O": 50.42076916997716,
                    "Cly": 0.0,
                    "Al2O3": 0.0
                }
            }
        ],
        "reentries": []
    },
    "1988-10-20": {
        "launches": [
            {
                "date": "1988-10-20",
                "id": "1988-095",
                "time": 15.72,
                "site": "",
                "rocket": "Proton-K/DM-2",
                "lat": 46.0,
                "lon": 63.0,
                "smc": false,
                "location": "NIIP-5, Baykonur, Kazakstan",
                "emissions": {
                    "BC": 2.1624429718465246,
                    "CO": 4.549336216904315,
                    "CO2": 146.13061133955784,
                    "NOx": 7.56439493696129,
                    "H2O": 199.63896572145242,
                    "Cly": 0.0,
                    "Al2O3": 0.0
                }
            }
        ],
        "reentries": []
    },
    "1988-10-25": {
        "launches": [
            {
                "date": "1988-10-25",
                "id": "1988-096",
                "time": 18.03,
                "site": "",
                "rocket": "Molniya 8K78M",
                "lat": 62.9,
                "lon": 40.5,
                "smc": false,
                "location": "53-y Nauchno-Issledovatelskiy Ispitatelniy Poligon,",
                "emissions": {
                    "BC": 0.8439179645528487,
                    "CO": 7.583947288229512,
                    "CO2": 68.15512312562008,
                    "NOx": 0.28034954692485065,
                    "H2O": 30.246600212912394,
                    "Cly": 0.0,
                    "Al2O3": 0.0
                }
            }
        ],
        "reentries": []
    },
    "1988-10-27": {
        "launches": [
            {
                "date": "1988-10-27",
                "id": "1988-097",
                "time": 11.52,
                "site": "",
                "rocket": "Soyuz-U",
                "lat": 62.9,
                "lon": 40.5,
                "smc": false,
                "location": "53-y Nauchno-Issledovatelskiy Ispitatelniy Poligon,",
                "emissions": {
                    "BC": 1.0935036055473257,
                    "CO": 8.366101332339973,
                    "CO2": 120.33284918913668,
                    "NOx": 0.5917722364437797,
                    "H2O": 50.42076916997716,
                    "Cly": 0.0,
                    "Al2O3": 0.0
                }
            }
        ],
        "reentries": []
    },
    "1988-10-28": {
        "launches": [
            {
                "date": "1988-10-28",
                "id": "1988-098",
                "time": 2.28,
                "site": "",
                "rocket": "Ariane 2",
                "lat": 5.2333,
                "lon": -52.7517,
                "smc": false,
                "location": "Centre Spatial Guyanais, Kourou, Guyane Francaise",
                "emissions": {
                    "BC": 0.7381911862351096,
                    "CO": 1.3767662995179062,
                    "CO2": 49.09244711092098,
                    "NOx": 2.5212627396383143,
                    "H2O": 66.75833089907933,
                    "Cly": 0.0,
                    "Al2O3": 0.0
                }
            }
        ],
        "reentries": []
    },
    "1988-11-06": {
        "launches": [
            {
                "date": "1988-11-06",
                "id": "1988-099",
                "time": 18.05,
                "site": "",
                "rocket": "Titan 34D",
                "lat": 34.63,
                "lon": -120.61,
                "smc": false,
                "location": "South Vandenberg AFB, California",
                "emissions": {
                    "BC": 1.6464728026419067,
                    "CO": 3.6487545435519553,
                    "CO2": 118.59358042241334,
                    "NOx": 2.406653727542141,
                    "H2O": 144.04455084546026,
                    "Cly": 45.65677908058751,
                    "Al2O3": 69.01119999999999
                }
            }
        ],
        "reentries": []
    },
    "1988-11-11": {
        "launches": [],
        "reentries": []
    },
    "1988-11-15": {
        "launches": [
            {
                "date": "1988-11-15",
                "id": "1988-100",
                "time": 3.0,
                "site": "",
                "rocket": "Energiya/Buran",
                "lat": 46.0,
                "lon": 63.0,
                "smc": false,
                "location": "NIIP-5, Baykonur, Kazakstan",
                "emissions": {
                    "BC": 2.3540517367806664,
                    "CO": 10.141050697242456,
                    "CO2": 345.63430966848836,
                    "NOx": 4.386962253074119,
                    "H2O": 812.9447197460305,
                    "Cly": 0.0,
                    "Al2O3": 0.0
                }
            }
        ],
        "reentries": []
    },
    "1988-11-18": {
        "launches": [
            {
                "date": "1988-11-18",
                "id": "1988-101",
                "time": 0.2,
                "site": "",
                "rocket": "Tsiklon-2",
                "lat": 46.0,
                "lon": 63.0,
                "smc": false,
                "location": "NIIP-5, Baykonur, Kazakstan",
                "emissions": {
                    "BC": 0.7329019836116208,
                    "CO": 1.8073526141153948,
                    "CO2": 33.82619343615902,
                    "NOx": 1.6917349611348786,
                    "H2O": 47.755854171416516,
                    "Cly": 0.0,
                    "Al2O3": 0.0
                }
            }
        ],
        "reentries": []
    },
    "1988-11-23": {
        "launches": [
            {
                "date": "1988-11-23",
                "id": "1988-102",
                "time": 14.83,
                "site": "",
                "rocket": "Zenit-2",
                "lat": 46.0,
                "lon": 63.0,
                "smc": false,
                "location": "NIIP-5, Baykonur, Kazakstan",
                "emissions": {
                    "BC": 2.700607972678415,
                    "CO": 18.00724294192844,
                    "CO2": 311.7858082387762,
                    "NOx": 1.5416768501467986,
                    "H2O": 128.46366210822114,
                    "Cly": 0.0,
                    "Al2O3": 0.0
                }
            }
        ],
        "reentries": []
    },
    "1988-11-24": {
        "launches": [
            {
                "date": "1988-11-24",
                "id": "1988-103",
                "time": 14.83,
                "site": "",
                "rocket": "Soyuz-U",
                "lat": 62.9,
                "lon": 40.5,
                "smc": false,
                "location": "53-y Nauchno-Issledovatelskiy Ispitatelniy Poligon,",
                "emissions": {
                    "BC": 1.0935036055473257,
                    "CO": 8.366101332339973,
                    "CO2": 120.33284918913668,
                    "NOx": 0.5917722364437797,
                    "H2O": 50.42076916997716,
                    "Cly": 0.0,
                    "Al2O3": 0.0
                }
            }
        ],
        "reentries": []
    },
    "1988-11-26": {
        "launches": [
            {
                "date": "1988-11-26",
                "id": "1988-104",
                "time": 15.82,
                "site": "",
                "rocket": "Soyuz-U2",
                "lat": 46.0,
                "lon": 63.0,
                "smc": false,
                "location": "NIIP-5, Baykonur, Kazakstan",
                "emissions": {
                    "BC": 1.0935036055473257,
                    "CO": 8.366101332339973,
                    "CO2": 120.33284918913668,
                    "NOx": 0.5917722364437797,
                    "H2O": 50.42076916997716,
                    "Cly": 0.0,
                    "Al2O3": 0.0
                }
            }
        ],
        "reentries": []
    },
    "1988-11-30": {
        "launches": [
            {
                "date": "1988-11-30",
                "id": "1988-105",
                "time": 9.0,
                "site": "",
                "rocket": "Soyuz-U",
                "lat": 46.0,
                "lon": 63.0,
                "smc": false,
                "location": "NIIP-5, Baykonur, Kazakstan",
                "emissions": {
                    "BC": 1.0935036055473257,
                    "CO": 8.366101332339973,
                    "CO2": 120.33284918913668,
                    "NOx": 0.5917722364437797,
                    "H2O": 50.42076916997716,
                    "Cly": 0.0,
                    "Al2O3": 0.0
                }
            }
        ],
        "reentries": []
    },
    "1988-12-02": {
        "launches": [
            {
                "date": "1988-12-02",
                "id": "1988-106",
                "time": 14.5,
                "site": "",
                "rocket": "Space Shuttle",
                "lat": 28.6083,
                "lon": -80.6041,
                "smc": false,
                "location": "NASA John F. Kennedy Space Center, Florida",
                "emissions": {
                    "BC": 1.9945134389312427,
                    "CO": 3.0535543664846507,
                    "CO2": 230.47350418889712,
                    "NOx": 3.297110619897022,
                    "H2O": 537.9217532925974,
                    "Cly": 108.93395922362025,
                    "Al2O3": 164.65599999999995
                }
            }
        ],
        "reentries": []
    },
    "1988-12-08": {
        "launches": [
            {
                "date": "1988-12-08",
                "id": "1988-107",
                "time": 14.83,
                "site": "",
                "rocket": "Soyuz-U-PVB",
                "lat": 62.9,
                "lon": 40.5,
                "smc": false,
                "location": "53-y Nauchno-Issledovatelskiy Ispitatelniy Poligon,",
                "emissions": {
                    "BC": 1.0720628966110188,
                    "CO": 8.246379552389595,
                    "CO2": 123.3954888630108,
                    "NOx": 0.622384918322759,
                    "H2O": 51.50661211767427,
                    "Cly": 0.0,
                    "Al2O3": 0.0
                }
            }
        ],
        "reentries": []
    },
    "1988-12-10": {
        "launches": [
            {
                "date": "1988-12-10",
                "id": "1988-108",
                "time": 11.9,
                "site": "",
                "rocket": "Proton-K/DM-2",
                "lat": 46.0,
                "lon": 63.0,
                "smc": false,
                "location": "NIIP-5, Baykonur, Kazakstan",
                "emissions": {
                    "BC": 2.1624429718465246,
                    "CO": 4.549336216904315,
                    "CO2": 146.13061133955784,
                    "NOx": 7.56439493696129,
                    "H2O": 199.63896572145242,
                    "Cly": 0.0,
                    "Al2O3": 0.0
                }
            }
        ],
        "reentries": []
    },
    "1988-12-11": {
        "launches": [
            {
                "date": "1988-12-11",
                "id": "1988-109",
                "time": 0.55,
                "site": "",
                "rocket": "Ariane 44LP",
                "lat": 5.2333,
                "lon": -52.7517,
                "smc": false,
                "location": "Centre Spatial Guyanais, Kourou, Guyane Francaise",
                "emissions": {
                    "BC": 1.091537267852126,
                    "CO": 2.656575886197079,
                    "CO2": 53.081778242641334,
                    "NOx": 2.4996192907592674,
                    "H2O": 73.76576560863481,
                    "Cly": 2.061499217008257,
                    "Al2O3": 3.1160000000000005
                }
            }
        ],
        "reentries": []
    },
    "1988-12-16": {
        "launches": [
            {
                "date": "1988-12-16",
                "id": "1988-110",
                "time": 19.0,
                "site": "",
                "rocket": "Soyuz-U",
                "lat": 62.9,
                "lon": 40.5,
                "smc": false,
                "location": "53-y Nauchno-Issledovatelskiy Ispitatelniy Poligon,",
                "emissions": {
                    "BC": 1.0935036055473257,
                    "CO": 8.366101332339973,
                    "CO2": 120.33284918913668,
                    "NOx": 0.5917722364437797,
                    "H2O": 50.42076916997716,
                    "Cly": 0.0,
                    "Al2O3": 0.0
                }
            }
        ],
        "reentries": []
    },
    "1988-12-22": {
        "launches": [
            {
                "date": "1988-12-22",
                "id": "1988-111",
                "time": 12.67,
                "site": "",
                "rocket": "Long March (CZ) 3",
                "lat": 28.2472,
                "lon": 102.0291,
                "smc": false,
                "location": "Xichang Space Center (Songlin), Sichuan, China",
                "emissions": {
                    "BC": 0.9217730900885759,
                    "CO": 1.681752841133059,
                    "CO2": 62.24357906277549,
                    "NOx": 3.1986867978037994,
                    "H2O": 84.51126659148143,
                    "Cly": 0.0,
                    "Al2O3": 0.0
                }
            },
            {
                "date": "1988-12-22",
                "id": "1988-112",
                "time": 14.25,
                "site": "",
                "rocket": "Molniya 8K78M",
                "lat": 62.9,
                "lon": 40.5,
                "smc": false,
                "location": "53-y Nauchno-Issledovatelskiy Ispitatelniy Poligon,",
                "emissions": {
                    "BC": 0.8439179645528487,
                    "CO": 7.583947288229512,
                    "CO2": 68.15512312562008,
                    "NOx": 0.28034954692485065,
                    "H2O": 30.246600212912394,
                    "Cly": 0.0,
                    "Al2O3": 0.0
                }
            }
        ],
        "reentries": []
    },
    "1988-12-23": {
        "launches": [
            {
                "date": "1988-12-23",
                "id": "1988-113",
                "time": 7.33,
                "site": "",
                "rocket": "Tsiklon-3",
                "lat": 62.9,
                "lon": 40.5,
                "smc": false,
                "location": "53-y Nauchno-Issledovatelskiy Ispitatelniy Poligon,",
                "emissions": {
                    "BC": 0.6868747189134614,
                    "CO": 1.4627346627604858,
                    "CO2": 41.10299779988749,
                    "NOx": 2.1011553614862866,
                    "H2O": 56.52834032917984,
                    "Cly": 0.0,
                    "Al2O3": 0.0
                }
            }
        ],
        "reentries": []
    },
    "1988-12-25": {
        "launches": [
            {
                "date": "1988-12-25",
                "id": "1988-114",
                "time": 4.18,
                "site": "",
                "rocket": "Soyuz-U2",
                "lat": 46.0,
                "lon": 63.0,
                "smc": false,
                "location": "NIIP-5, Baykonur, Kazakstan",
                "emissions": {
                    "BC": 1.0935036055473257,
                    "CO": 8.366101332339973,
                    "CO2": 120.33284918913668,
                    "NOx": 0.5917722364437797,
                    "H2O": 50.42076916997716,
                    "Cly": 0.0,
                    "Al2O3": 0.0
                }
            }
        ],
        "reentries": []
    },
    "1988-12-28": {
        "launches": [
            {
                "date": "1988-12-28",
                "id": "1988-115",
                "time": 5.45,
                "site": "",
                "rocket": "Molniya 8K78M",
                "lat": 62.9,
                "lon": 40.5,
                "smc": false,
                "location": "53-y Nauchno-Issledovatelskiy Ispitatelniy Poligon,",
                "emissions": {
                    "BC": 0.8439179645528487,
                    "CO": 7.583947288229512,
                    "CO2": 68.15512312562008,
                    "NOx": 0.28034954692485065,
                    "H2O": 30.246600212912394,
                    "Cly": 0.0,
                    "Al2O3": 0.0
                }
            }
        ],
        "reentries": []
    },
    "1988-12-29": {
        "launches": [
            {
                "date": "1988-12-29",
                "id": "1988-116",
                "time": 10.0,
                "site": "",
                "rocket": "Soyuz-U",
                "lat": 46.0,
                "lon": 63.0,
                "smc": false,
                "location": "NIIP-5, Baykonur, Kazakstan",
                "emissions": {
                    "BC": 1.0935036055473257,
                    "CO": 8.366101332339973,
                    "CO2": 120.33284918913668,
                    "NOx": 0.5917722364437797,
                    "H2O": 50.42076916997716,
                    "Cly": 0.0,
                    "Al2O3": 0.0
                }
            }
        ],
        "reentries": []
    }
}